django_stash_tag/__init__.py
django_stash_tag/templatetags/__init__.py
django_stash_tag/templatetags/stash.py
django_stash_tag-19.3.0.dist-info/METADATA
django_stash_tag-19.3.0.dist-info/WHEEL
django_stash_tag-19.3.0.dist-info/top_level.txt
django_stash_tag-19.3.0.dist-info/RECORD
