Metadata-Version: 2.1
Name: django-stash-tag
Version: 19.3.0
Summary: A Django Template Tag that stashes content for dynamic reuse.
Home-page: https://github.com/l4nk332/django-stash-tag
Author: Ian Jabour
Author-email: l4nk332@gmail.com
License: MIT
Keywords: django,templatetag,template,tag,stash,dynamic
Platform: UNKNOWN
Classifier: License :: OSI Approved :: MIT License
Classifier: Programming Language :: Python :: 3
Classifier: Programming Language :: Python :: 2.7
Requires-Dist: django (>=1.11)
